clabtoolkit/__init__.py
clabtoolkit/bidstools.py
clabtoolkit/build_visualization_layout.py
clabtoolkit/colorstools.py
clabtoolkit/connectivitytools.py
clabtoolkit/dicomtools.py
clabtoolkit/dwitools.py
clabtoolkit/freesurfertools.py
clabtoolkit/imagetools.py
clabtoolkit/misctools.py
clabtoolkit/morphometrytools.py
clabtoolkit/networktools.py
clabtoolkit/parcellationtools.py
clabtoolkit/pipelinetools.py
clabtoolkit/plottools.py
clabtoolkit/pointstools.py
clabtoolkit/qcqatools.py
clabtoolkit/segmentationtools.py
clabtoolkit/surfacetools.py
clabtoolkit/tracttools.py
clabtoolkit/visualization_utils.py
clabtoolkit/visualizationtools.py
clabtoolkit/config/bids.json
clabtoolkit/config/config.json
clabtoolkit/config/lobes.json
clabtoolkit/config/stats_mapping.json
clabtoolkit/config/viz_views.json
clabtoolkit/config/viz_views_test.json
clabtoolkit-0.4.0.dist-info/licenses/AUTHORS.rst
clabtoolkit-0.4.0.dist-info/licenses/LICENSE
clabtoolkit-0.4.0.dist-info/METADATA
clabtoolkit-0.4.0.dist-info/WHEEL
clabtoolkit-0.4.0.dist-info/top_level.txt
clabtoolkit-0.4.0.dist-info/RECORD
