Metadata-Version: 2.4
Name: clabtoolkit
Version: 0.4.0
Summary: A comprehensive toolkit for neuroimaging data processing and analysis
Author-email: Yasser Alemán-Gómez <yasseraleman@protonmail.com>
Maintainer-email: Yasser Alemán-Gómez <yasseraleman@protonmail.com>
License-Expression: Apache-2.0
Project-URL: Homepage, https://github.com/connectomicslab/clabtoolkit
Project-URL: Repository, https://github.com/connectomicslab/clabtoolkit
Project-URL: Documentation, https://clabtoolkit.readthedocs.io
Project-URL: Bug Tracker, https://github.com/connectomicslab/clabtoolkit/issues
Keywords: neuroimaging,image-processing,bids,freesurfer,connectivity
Classifier: Development Status :: 4 - Beta
Classifier: Intended Audience :: Science/Research
Classifier: Intended Audience :: Developers
Classifier: Natural Language :: English
Classifier: Operating System :: OS Independent
Classifier: Programming Language :: Python :: 3
Classifier: Programming Language :: Python :: 3.9
Classifier: Programming Language :: Python :: 3.10
Classifier: Programming Language :: Python :: 3.11
Classifier: Programming Language :: Python :: 3.12
Classifier: Topic :: Scientific/Engineering :: Medical Science Apps.
Classifier: Topic :: Scientific/Engineering :: Image Processing
Requires-Python: >=3.9
License-File: LICENSE
License-File: AUTHORS.rst
Requires-Dist: nibabel>=5.3.2
Requires-Dist: numpy>=1.23.5
Requires-Dist: pandas>=2.3.1
Requires-Dist: pydicom>=3.0.1
Requires-Dist: rich>=14.1.0
Requires-Dist: scipy>=1.16.0
Requires-Dist: setuptools>=80.9.0
Requires-Dist: scikit-image>=0.25.2
Requires-Dist: h5py>=3.14.0
Requires-Dist: matplotlib>=3.10.3
Requires-Dist: pyvista>=0.45.3
Requires-Dist: nilearn>=0.12.0
Requires-Dist: joblib>=1.5.1
Provides-Extra: dev
Requires-Dist: pytest>=8.4.1; extra == "dev"
Requires-Dist: pytest-cov>=6.2.1; extra == "dev"
Requires-Dist: black>=25.1.0; extra == "dev"
Requires-Dist: ruff>=0.12.5; extra == "dev"
Requires-Dist: mypy>=1.17.0; extra == "dev"
Requires-Dist: pre-commit>=4.2.0; extra == "dev"
Requires-Dist: tox>=4.28.1; extra == "dev"
Requires-Dist: termcolor>=3.1.0; extra == "dev"
Requires-Dist: tabulate>=0.9.0; extra == "dev"
Provides-Extra: docs
Requires-Dist: sphinx>=8.2.3; extra == "docs"
Requires-Dist: sphinx-rtd-theme>=3.0.2; extra == "docs"
Requires-Dist: myst-parser>=4.0.1; extra == "docs"
Provides-Extra: test
Requires-Dist: pytest>=8.4.1; extra == "test"
Requires-Dist: pytest-cov>=6.2.1; extra == "test"
Requires-Dist: pytest-xdist>=3.8.0; extra == "test"
Dynamic: license-file
